mobile_app_version/__init__.py
mobile_app_version/admin.py
mobile_app_version/apps.py
mobile_app_version/messages.py
mobile_app_version/middlewares.py
mobile_app_version/models.py
mobile_app_version/paginations.py
mobile_app_version/serializers.py
mobile_app_version/tests.py
mobile_app_version/urls.py
mobile_app_version/validators.py
mobile_app_version/views.py
django_mobile_app_version-1.2.0.dist-info/METADATA
django_mobile_app_version-1.2.0.dist-info/WHEEL
django_mobile_app_version-1.2.0.dist-info/top_level.txt
django_mobile_app_version-1.2.0.dist-info/RECORD
